<?xml version="1.0" encoding="utf-8"?>
<savedquery unmodified="1">
  <isquickfindquery>0</isquickfindquery>
  <isprivate>0</isprivate>
  <isdefault>1</isdefault>
  <returnedtypecode>1001</returnedtypecode>
  <savedqueryid>{a1bacafe-3823-494a-8fe2-84af03cc25b3}</savedqueryid>
  <queryapi></queryapi>
  <querytype>8192</querytype>
  <fetchxml>
    <fetch version="1.0" output-format="xml-platform" mapping="logical" distinct="false">
      <entity name="activitymimeattachment">
        <attribute name="activitymimeattachmentidunique" />
        <attribute name="activitymimeattachmentid" />
        <filter type="and">
          <condition attribute="filesize" operator="lt" value="1048576" />
        </filter>
      </entity>
    </fetch>
  </fetchxml>
  <IntroducedVersion>5.0.0.0</IntroducedVersion>
  <LocalizedNames>
    <LocalizedName description="Attachments on Downloaded Email Messages" languagecode="1033" />
  </LocalizedNames>
  <Descriptions>
    <Description description="Attachments under 1 MB on email messages I have downloaded" languagecode="1033" />
  </Descriptions>
</savedquery>