<?xml version="1.0" encoding="utf-8"?>
<savedquery>
  <IsCustomizable>1</IsCustomizable>
  <CanBeDeleted>1</CanBeDeleted>
  <isquickfindquery>0</isquickfindquery>
  <isprivate>0</isprivate>
  <isdefault>0</isdefault>
  <returnedtypecode>112</returnedtypecode>
  <savedqueryid>{ebdc0ca5-9610-e711-810a-3863bb34fb48}</savedqueryid>
  <layoutxml>
    <grid name="resultset" object="112" jump="title" select="1" icon="1" preview="1">
      <row name="result" id="incidentid">
        <cell name="ticketnumber" width="150" />
        <cell name="tc_casetypeid" width="125" imageproviderfunctionname="" imageproviderwebresource="$webresource:" />
        <cell name="prioritycode" width="100" />
        <cell name="caseorigincode" width="100" />
        <cell name="customerid" width="150" imageproviderfunctionname="" imageproviderwebresource="$webresource:" />
        <cell name="ownerid" width="125" imageproviderfunctionname="" imageproviderwebresource="$webresource:" />
        <cell name="statuscode" width="125" imageproviderfunctionname="" imageproviderwebresource="$webresource:" />
        <cell name="createdon" width="100" />
        <cell name="a_cdf05794a0ec49a3b2548ed7aa26cdd5.tc_language" width="100" disableSorting="1" />
        <cell name="ab.businessunitid" width="100" disableSorting="1" />
      </row>
    </grid>
  </layoutxml>
  <querytype>0</querytype>
  <fetchxml>
    <fetch version="1.0" output-format="xml-platform" mapping="logical" distinct="false">
      <entity name="incident">
        <attribute name="ticketnumber" />
        <attribute name="tc_casetypeid" />
        <attribute name="statuscode" />
        <attribute name="prioritycode" />
        <attribute name="ownerid" />
        <attribute name="caseorigincode" />
        <attribute name="customerid" />
        <attribute name="createdon" />
        <order attribute="createdon" descending="true" />
        <link-entity name="contact" from="contactid" to="customerid" visible="false" link-type="outer" alias="a_cdf05794a0ec49a3b2548ed7aa26cdd5">
          <attribute name="tc_language" />
        </link-entity>
        <link-entity name="systemuser" from="systemuserid" to="owninguser" alias="ab">
          <filter type="and">
            <condition attribute="parentsystemuserid" operator="eq-userid" />
            <condition attribute="businessunitid" operator="eq-businessid" />
          </filter>
          <attribute name="businessunitid" />
        </link-entity>
        <attribute name="incidentid" />
      </entity>
    </fetch>
  </fetchxml>
  <IntroducedVersion>1.0.0.51</IntroducedVersion>
  <LocalizedNames>
    <LocalizedName description="My Cases By Team" languagecode="1033" />
  </LocalizedNames>
</savedquery>